aisearch/__init__.py
aisearch/ai_search.py
aisearch-0.0.1.dist-info/METADATA
aisearch-0.0.1.dist-info/WHEEL
aisearch-0.0.1.dist-info/top_level.txt
aisearch-0.0.1.dist-info/RECORD
