Metadata-Version: 2.1
Name: aisearch
Version: 0.0.1
Summary: This project provides an easy way to search  using AI
Home-page: https://gitee.com/make-one/sddad
Author: LiuRuiYi
Author-email: 2352129115@qq.com
